{"@context":["https://www.w3.org/ns/did/v1","https://w3id.org/security/suites/jws-2020/v1"],"id":"did:web:worldhealthorganization.github.io:tng-cdn-dev:v2.0.0:trustlist-ref:RACSEL-DDVC:URY","controller":"did:web:worldhealthorganization.github.io:tng-cdn-dev:v2.0.0:trustlist-ref:RACSEL-DDVC:URY","verificationMethod":["did:web:worldhealthorganization.github.io:tng-cdn-dev:v2.0.0:trustlist:RACSEL-DDVC:URY#4sgvGRlLOak%3D","did:web:tng-cdn-dev.who.int:trustlist"],"proof":{"type":"JsonWebSignature2020","created":"2024-06-04T07:50:54Z","nonce":"W3Nu8qV9lXuisGsO8VW8raIWiDrxMegM","proofPurpose":"assertionMethod","verificationMethod":"did:web:raw:githubusercontent:com:WorldHealthOrganization:tng-participants-dev:main:WHO:signing:DID","jws":"eyJiNjQiOmZhbHNlLCJjcml0IjpbImI2NCJdLCJhbGciOiJFQyJ9..MEQCIC_X3hktZN4OWkMeBEQeGJIDxzJac1w2ndiOMHWQfei_AiAW2P3T1WsAv94TtqqlzSU57Ps9h43oDdq_ObpJ-3ZemQ"}}