{"@context":["https://www.w3.org/ns/did/v1","https://w3id.org/security/suites/jws-2020/v1"],"id":"did:web:worldhealthorganization.github.io:tng-cdn-dev:v2.0.0:trustlist-ref:RACSEL-DDVC:URY","controller":"did:web:worldhealthorganization.github.io:tng-cdn-dev:v2.0.0:trustlist-ref:RACSEL-DDVC:URY","verificationMethod":["did:web:worldhealthorganization.github.io:tng-cdn-dev:v2.0.0:trustlist:RACSEL-DDVC:URY#4sgvGRlLOak%3D","did:web:tng-cdn-dev.who.int:trustlist"],"proof":{"type":"JsonWebSignature2020","created":"2024-06-09T04:25:07Z","nonce":"9zqLBb2J2UuLMKIidqp4ZKCnQp30qgUs","proofPurpose":"assertionMethod","verificationMethod":"did:web:raw:githubusercontent:com:WorldHealthOrganization:tng-participants-dev:main:WHO:signing:DID","jws":"eyJiNjQiOmZhbHNlLCJjcml0IjpbImI2NCJdLCJhbGciOiJFQyJ9..MEUCIQCW8oqp_rdMsC60uvARFU05HEF0C4PaUYM_oN1CBqacaQIgG2okjg7x4DralSvM77Q6TZjOpwMHpXfBFQgdcUZCh64"}}