{"@context":["https://www.w3.org/ns/did/v1","https://w3id.org/security/suites/jws-2020/v1"],"id":"did:web:worldhealthorganization.github.io:tng-cdn-dev:v2.0.0:trustlist-ref:DCC:TGO:SCA","controller":"did:web:worldhealthorganization.github.io:tng-cdn-dev:v2.0.0:trustlist-ref:DCC:TGO:SCA","verificationMethod":["did:web:worldhealthorganization.github.io:tng-cdn-dev:v2.0.0:trustlist:DCC:TGO:SCA#zn4yqPfW35o%3D","did:web:tng-cdn-dev.who.int:trustlist"],"proof":{"type":"JsonWebSignature2020","created":"2024-06-06T01:25:09Z","nonce":"ZojlW09bjBfdCLEWvk2E7P1ROBHe7vVc","proofPurpose":"assertionMethod","verificationMethod":"did:web:raw:githubusercontent:com:WorldHealthOrganization:tng-participants-dev:main:WHO:signing:DID","jws":"eyJiNjQiOmZhbHNlLCJjcml0IjpbImI2NCJdLCJhbGciOiJFQyJ9..MEUCIQCoY9aaevo3R2UBYZtYxfPyyfISbcvlxLRYFVU0r-LWWAIgOSBZcxZ_1V3KkO71e55oX7FmGdswvjZBj870JZEqyfY"}}