{"@context":["https://www.w3.org/ns/did/v1","https://w3id.org/security/suites/jws-2020/v1"],"id":"did:web:worldhealthorganization.github.io:tng-cdn-dev:v2.0.0:trustlist-ref:DCC:IDN:SCA","controller":"did:web:worldhealthorganization.github.io:tng-cdn-dev:v2.0.0:trustlist-ref:DCC:IDN:SCA","verificationMethod":["did:web:worldhealthorganization.github.io:tng-cdn-dev:v2.0.0:trustlist:DCC:IDN:SCA#SY5oBUHoQKA%3D","did:web:tng-cdn-dev.who.int:trustlist"],"proof":{"type":"JsonWebSignature2020","created":"2024-06-05T23:55:08Z","nonce":"ByPRMtBkjKxZYj1vd01wAmAURwDPxj9g","proofPurpose":"assertionMethod","verificationMethod":"did:web:raw:githubusercontent:com:WorldHealthOrganization:tng-participants-dev:main:WHO:signing:DID","jws":"eyJiNjQiOmZhbHNlLCJjcml0IjpbImI2NCJdLCJhbGciOiJFQyJ9..MEYCIQD2N2Vu1AdyY6mwGVu4J5b1FNjVzOe1PbB8wh3kV5RplAIhANrXYqpoiN5Pz-6lm_KLvFaIE1LlO1RQNBrqm7nDOi0m"}}