{"@context":["https://www.w3.org/ns/did/v1","https://w3id.org/security/suites/jws-2020/v1"],"id":"did:web:worldhealthorganization.github.io:tng-cdn-dev:v2.0.0:trustlist-ref:-:XXO:SCA","controller":"did:web:worldhealthorganization.github.io:tng-cdn-dev:v2.0.0:trustlist-ref:-:XXO:SCA","verificationMethod":["did:web:worldhealthorganization.github.io:tng-cdn-dev:v2.0.0:trustlist:-:XXO:SCA#PU%2BS3zhQK0g%3D","did:web:worldhealthorganization.github.io:tng-cdn-dev:v2.0.0:trustlist:-:XXO:SCA#SVYR4b5HLS0%3D","did:web:tng-cdn-dev.who.int:trustlist"],"proof":{"type":"JsonWebSignature2020","created":"2024-06-08T10:50:10Z","nonce":"xYHE1vUPPlYXrD4mRtChBya0Vb6xDSG8","proofPurpose":"assertionMethod","verificationMethod":"did:web:raw:githubusercontent:com:WorldHealthOrganization:tng-participants-dev:main:WHO:signing:DID","jws":"eyJiNjQiOmZhbHNlLCJjcml0IjpbImI2NCJdLCJhbGciOiJFQyJ9..MEQCIHM7WU9GXOXX23nNkcGD-Xz00A3EDVGMiT3JNDO2Vi2-AiAF4aM2c2K-Opl8d0sK1gCrb_BUieWCYK6czpXhOfl5KQ"}}