{"@context":["https://www.w3.org/ns/did/v1","https://w3id.org/security/suites/jws-2020/v1"],"id":"did:web:worldhealthorganization.github.io:tng-cdn-dev:v2.0.0:trustlist-ref:-:HND:SCA","controller":"did:web:worldhealthorganization.github.io:tng-cdn-dev:v2.0.0:trustlist-ref:-:HND:SCA","verificationMethod":["did:web:worldhealthorganization.github.io:tng-cdn-dev:v2.0.0:trustlist:-:HND:SCA#TA7FfYsm528%3D","did:web:tng-cdn-dev.who.int:trustlist"],"proof":{"type":"JsonWebSignature2020","created":"2024-05-29T09:25:07Z","nonce":"iYElvbG81igA1JpVt2E6lYOPbhnWNZXw","proofPurpose":"assertionMethod","verificationMethod":"did:web:dummy.net","jws":"eyJiNjQiOmZhbHNlLCJjcml0IjpbImI2NCJdLCJhbGciOiJFQyJ9..Cdaq60pekoeQiMVizV0ywJrXc-VtCmRrLAsL7y-Vdy0"}}