{"@context":["https://www.w3.org/ns/did/v1","https://w3id.org/security/suites/jws-2020/v1"],"id":"did:web:worldhealthorganization.github.io:tng-cdn-dev:v2.0.0:trustlist-ref:DCC:SLV","controller":"did:web:worldhealthorganization.github.io:tng-cdn-dev:v2.0.0:trustlist-ref:DCC:SLV","verificationMethod":["did:web:worldhealthorganization.github.io:tng-cdn-dev:v2.0.0:trustlist:DCC:SLV#hn8pla07fm0%3D","did:web:tng-cdn-dev.who.int:trustlist"],"proof":{"type":"JsonWebSignature2020","created":"2024-06-04T22:55:07Z","nonce":"2fKMvfmo0jsdwb69uTJNeiJL64KQEwZE","proofPurpose":"assertionMethod","verificationMethod":"did:web:raw:githubusercontent:com:WorldHealthOrganization:tng-participants-dev:main:WHO:signing:DID","jws":"eyJiNjQiOmZhbHNlLCJjcml0IjpbImI2NCJdLCJhbGciOiJFQyJ9..MEYCIQDLt-8E-j_sc1DbA-2tsIUuVWMs3eBDULnpdRRcg3hGBQIhANyyXAffFqBFBnKvQih9pFMvbfVNWYVoi7uuy0go5tWD"}}