{"@context":["https://www.w3.org/ns/did/v1","https://w3id.org/security/suites/jws-2020/v1"],"id":"did:web:worldhealthorganization.github.io:tng-cdn-dev:v2.0.0:trustlist-ref:-:XCL:SCA","controller":"did:web:worldhealthorganization.github.io:tng-cdn-dev:v2.0.0:trustlist-ref:-:XCL:SCA","verificationMethod":["did:web:worldhealthorganization.github.io:tng-cdn-dev:v2.0.0:trustlist:-:XCL:SCA#2RIYRNJvPBg%3D","did:web:worldhealthorganization.github.io:tng-cdn-dev:v2.0.0:trustlist:-:XCL:SCA#3wiKBCaFuok%3D","did:web:worldhealthorganization.github.io:tng-cdn-dev:v2.0.0:trustlist:-:XCL:SCA#8nAX0I7m7A0%3D","did:web:tng-cdn-dev.who.int:trustlist"],"proof":{"type":"JsonWebSignature2020","created":"2024-06-05T08:25:08Z","nonce":"Zq3XZymBjC2QnRtJhwy25aTB1Di6zX9c","proofPurpose":"assertionMethod","verificationMethod":"did:web:raw:githubusercontent:com:WorldHealthOrganization:tng-participants-dev:main:WHO:signing:DID","jws":"eyJiNjQiOmZhbHNlLCJjcml0IjpbImI2NCJdLCJhbGciOiJFQyJ9..MEUCIGrVvAGtBmb-tr7DYN2kJ3i8upVksnzCKsHJXjXnc-_fAiEAt679nXHmw85gCz3VtgOMkute45Pv8DLnrnwtl6nguKE"}}