{"@context":["https://www.w3.org/ns/did/v1","https://w3id.org/security/suites/jws-2020/v1"],"id":"did:web:worldhealthorganization.github.io:tng-cdn-dev:v2.0.0:trustlist-ref:RACSEL-DDVC:COL","controller":"did:web:worldhealthorganization.github.io:tng-cdn-dev:v2.0.0:trustlist-ref:RACSEL-DDVC:COL","verificationMethod":["did:web:worldhealthorganization.github.io:tng-cdn-dev:v2.0.0:trustlist:RACSEL-DDVC:COL#iOtZ7lryNK4%3D","did:web:tng-cdn-dev.who.int:trustlist"],"proof":{"type":"JsonWebSignature2020","created":"2024-06-03T16:05:08Z","nonce":"DS2jsUJXgV9i8kiVkZTqt6N7lPWd94sS","proofPurpose":"assertionMethod","verificationMethod":"did:web:dummy.net","jws":"eyJiNjQiOmZhbHNlLCJjcml0IjpbImI2NCJdLCJhbGciOiJFQyJ9..MEYCIQDJF1Skdds1--9BNB6LH7gJaeQ-328Q1MaPebuM4JTJDwIhANsYZ4fBMkE645uvXoCa3Zq-uiyqLp8Y_qZECwaV6wjp"}}