{"@context":["https://www.w3.org/ns/did/v1","https://w3id.org/security/suites/jws-2020/v1"],"id":"did:web:worldhealthorganization.github.io:tng-cdn-dev:v2.0.0:trustlist-ref:-:GTM:DSC","controller":"did:web:worldhealthorganization.github.io:tng-cdn-dev:v2.0.0:trustlist-ref:-:GTM:DSC","verificationMethod":["did:web:worldhealthorganization.github.io:tng-cdn-dev:v2.0.0:trustlist:-:GTM:DSC#zF3bITactCQ%3D","did:web:tng-cdn-dev.who.int:trustlist"],"proof":{"type":"JsonWebSignature2020","created":"2024-06-04T19:05:56Z","nonce":"5qLkgE67PTL183jIIs6PGyEdy1LTtlQj","proofPurpose":"assertionMethod","verificationMethod":"did:web:raw:githubusercontent:com:WorldHealthOrganization:tng-participants-dev:main:WHO:signing:DID","jws":"eyJiNjQiOmZhbHNlLCJjcml0IjpbImI2NCJdLCJhbGciOiJFQyJ9..MEQCICuS7zhv2WXXn_J2BWUN3H3LOztyL2LbwyV9xxnMiXVqAiBkU6QPMKLXpLxxT_gcrvLMRuevSaw3kD6ehPBhuIccIg"}}