{"@context":["https://www.w3.org/ns/did/v1","https://w3id.org/security/suites/jws-2020/v1"],"id":"did:web:worldhealthorganization.github.io:tng-cdn-dev:v2.0.0:trustlist-ref:-:HND","controller":"did:web:worldhealthorganization.github.io:tng-cdn-dev:v2.0.0:trustlist-ref:-:HND","verificationMethod":["did:web:worldhealthorganization.github.io:tng-cdn-dev:v2.0.0:trustlist:-:HND#MljNbYidyn4%3D","did:web:worldhealthorganization.github.io:tng-cdn-dev:v2.0.0:trustlist:-:HND#TA7FfYsm528%3D","did:web:tng-cdn-dev.who.int:trustlist"],"proof":{"type":"JsonWebSignature2020","created":"2024-06-04T16:55:06Z","nonce":"mHp8i3kv6fRx1e8kO4LvuOse6yk3DJCc","proofPurpose":"assertionMethod","verificationMethod":"did:web:raw:githubusercontent:com:WorldHealthOrganization:tng-participants-dev:main:WHO:signing:DID","jws":"eyJiNjQiOmZhbHNlLCJjcml0IjpbImI2NCJdLCJhbGciOiJFQyJ9..MEUCIAl5c0B_G1zPQLi8auZFyILffZu7CstNPuq33brACgehAiEAg9b5iDKcXwluGdY963aB5-3ve4akmZOgJAgRL3RU7_g"}}