{"@context":["https://www.w3.org/ns/did/v1","https://w3id.org/security/suites/jws-2020/v1"],"id":"did:web:worldhealthorganization.github.io:tng-cdn-dev:v2.0.0:trustlist-ref:DCC:OMN:DSC","controller":"did:web:worldhealthorganization.github.io:tng-cdn-dev:v2.0.0:trustlist-ref:DCC:OMN:DSC","verificationMethod":["did:web:worldhealthorganization.github.io:tng-cdn-dev:v2.0.0:trustlist:DCC:OMN:DSC#dRyRUE1SS6o%3D","did:web:tng-cdn-dev.who.int:trustlist"],"proof":{"type":"JsonWebSignature2020","created":"2024-06-09T21:15:08Z","nonce":"r4zvse2yBOYbwJiMzPPGo4OeiLaT4Izz","proofPurpose":"assertionMethod","verificationMethod":"did:web:raw:githubusercontent:com:WorldHealthOrganization:tng-participants-dev:main:WHO:signing:DID","jws":"eyJiNjQiOmZhbHNlLCJjcml0IjpbImI2NCJdLCJhbGciOiJFQyJ9..MEUCIQDKMrTBkCLGY2IHtV-_1vp4qFDnNCs0YQfWy57f8KWPvgIgU4yay1UzNvmm3RYr4JtmHDwu3lYrJRxRDOWg1r9MhKI"}}