{"@context":["https://www.w3.org/ns/did/v1","https://w3id.org/security/suites/jws-2020/v1"],"id":"did:web:worldhealthorganization.github.io:tng-cdn-dev:v2.0.0:trustlist-ref:-:CRI:DSC","controller":"did:web:worldhealthorganization.github.io:tng-cdn-dev:v2.0.0:trustlist-ref:-:CRI:DSC","verificationMethod":["did:web:worldhealthorganization.github.io:tng-cdn-dev:v2.0.0:trustlist:-:CRI:DSC#cShS28q1XbM%3D","did:web:tng-cdn-dev.who.int:trustlist"],"proof":{"type":"JsonWebSignature2020","created":"2024-06-08T04:35:08Z","nonce":"wIxiksvYJ3XWaUfV6X1kBD7ZmRLmRuAk","proofPurpose":"assertionMethod","verificationMethod":"did:web:raw:githubusercontent:com:WorldHealthOrganization:tng-participants-dev:main:WHO:signing:DID","jws":"eyJiNjQiOmZhbHNlLCJjcml0IjpbImI2NCJdLCJhbGciOiJFQyJ9..MEYCIQCk_eXiPZdlVTwUVAz8GxLKH7Q2nvw2rt0D1o4t0HNqYAIhAM0V6_dDniG04ZALtZ-ACQYyK8mtzirfv_jHXRLgCeiL"}}