{"@context":["https://www.w3.org/ns/did/v1","https://w3id.org/security/suites/jws-2020/v1"],"id":"did:web:worldhealthorganization.github.io:tng-cdn-dev:v2.0.0:trustlist-ref:-:CRI","controller":"did:web:worldhealthorganization.github.io:tng-cdn-dev:v2.0.0:trustlist-ref:-:CRI","verificationMethod":["did:web:worldhealthorganization.github.io:tng-cdn-dev:v2.0.0:trustlist:-:CRI#TMS%2F0ppjZws%3D","did:web:worldhealthorganization.github.io:tng-cdn-dev:v2.0.0:trustlist:-:CRI#cShS28q1XbM%3D","did:web:tng-cdn-dev.who.int:trustlist"],"proof":{"type":"JsonWebSignature2020","created":"2024-06-09T17:20:06Z","nonce":"NTm8YU0Q6qtIBRdb4U80aWN6QJJRohrZ","proofPurpose":"assertionMethod","verificationMethod":"did:web:raw:githubusercontent:com:WorldHealthOrganization:tng-participants-dev:main:WHO:signing:DID","jws":"eyJiNjQiOmZhbHNlLCJjcml0IjpbImI2NCJdLCJhbGciOiJFQyJ9..MEUCIQChXRpPtao5NWx9QCs4c__Put2oPn_lDrfNs9e42Xdp1AIgOnyLGBp3pFhgWpHwM_Qa2dhNR8rW_faPHO7e2VQngVg"}}