{"@context":["https://www.w3.org/ns/did/v1","https://w3id.org/security/suites/jws-2020/v1"],"id":"did:web:abc:trustlist-ref:-:PAN:DSC","controller":"did:web:abc:trustlist-ref:-:PAN:DSC","verificationMethod":["did:web:abc:trustlist:-:PAN:DSC#sP828h0%2BjKc%3D","did:web:abc:trustlist:-:PAN:DSC#wjZSzRysxoY%3D","did:web:tng-cdn-dev.who.int:trustlist"],"proof":{"type":"JsonWebSignature2020","created":"2024-05-23T15:10:01Z","nonce":"sGOQuQv80UrfLVva5AV389DAsaU0YXRn","proofPurpose":"assertionMethod","verificationMethod":"did:web:dummy.net","jws":"eyJiNjQiOmZhbHNlLCJjcml0IjpbImI2NCJdLCJhbGciOiJFQyJ9..Ri-2TViVskZC7LxxL3eN3v3fRZv4rsE3VtM5zmqVgEs"}}