{"@context":["https://www.w3.org/ns/did/v1","https://w3id.org/security/suites/jws-2020/v1"],"id":"did:web:worldhealthorganization.github.io:tng-cdn-dev:v2.0.0:trustlist-ref:-:PRY:SCA","controller":"did:web:worldhealthorganization.github.io:tng-cdn-dev:v2.0.0:trustlist-ref:-:PRY:SCA","verificationMethod":["did:web:worldhealthorganization.github.io:tng-cdn-dev:v2.0.0:trustlist:-:PRY:SCA#HulZiaPtMTM%3D","did:web:tng-cdn-dev.who.int:trustlist"],"proof":{"type":"JsonWebSignature2020","created":"2024-05-28T20:40:52Z","nonce":"XkSPJkH3zzRCJ12fUVOrM4XW4siFVZQi","proofPurpose":"assertionMethod","verificationMethod":"did:web:dummy.net","jws":"eyJiNjQiOmZhbHNlLCJjcml0IjpbImI2NCJdLCJhbGciOiJFQyJ9..MLarWWfgVTCVlyUOAbHu4by4-ieu5SHU8--N40aaDrk"}}