{"@context":["https://www.w3.org/ns/did/v1","https://w3id.org/security/suites/jws-2020/v1"],"id":"did:web:worldhealthorganization.github.io:tng-cdn-dev:v2.0.0:trustlist-ref:-:CHL","controller":"did:web:worldhealthorganization.github.io:tng-cdn-dev:v2.0.0:trustlist-ref:-:CHL","verificationMethod":["did:web:worldhealthorganization.github.io:tng-cdn-dev:v2.0.0:trustlist:-:CHL#NI8FjFdN098%3D","did:web:worldhealthorganization.github.io:tng-cdn-dev:v2.0.0:trustlist:-:CHL#aQ7BMJAhsho%3D","did:web:tng-cdn-dev.who.int:trustlist"],"proof":{"type":"JsonWebSignature2020","created":"2024-06-07T11:50:09Z","nonce":"JmzuOXJxGmacXLN4TNbjEr7Y47bwEXX7","proofPurpose":"assertionMethod","verificationMethod":"did:web:raw:githubusercontent:com:WorldHealthOrganization:tng-participants-dev:main:WHO:signing:DID","jws":"eyJiNjQiOmZhbHNlLCJjcml0IjpbImI2NCJdLCJhbGciOiJFQyJ9..MEUCIDsi1xfHf1W9MmoWYHIxB-xSmy3sUoHvQKm1mvGEVtIaAiEAkVI7z6XiEPJmFdycpvz81vk4dvOg6SQCwkqlF1SFam8"}}