{"@context":["https://www.w3.org/ns/did/v1","https://w3id.org/security/suites/jws-2020/v1"],"id":"did:web:worldhealthorganization.github.io:tng-cdn-dev:v2.0.0:trustlist-ref:RACSEL-DDVC:PAN:SCA","controller":"did:web:worldhealthorganization.github.io:tng-cdn-dev:v2.0.0:trustlist-ref:RACSEL-DDVC:PAN:SCA","verificationMethod":["did:web:worldhealthorganization.github.io:tng-cdn-dev:v2.0.0:trustlist:RACSEL-DDVC:PAN:SCA#Q4iZty%2B3B5w%3D","did:web:tng-cdn-dev.who.int:trustlist"],"proof":{"type":"JsonWebSignature2020","created":"2024-06-05T04:56:04Z","nonce":"Evknlc8QCAoI3qYJS7tbFbr3AiMyNppc","proofPurpose":"assertionMethod","verificationMethod":"did:web:raw:githubusercontent:com:WorldHealthOrganization:tng-participants-dev:main:WHO:signing:DID","jws":"eyJiNjQiOmZhbHNlLCJjcml0IjpbImI2NCJdLCJhbGciOiJFQyJ9..MEUCIBAZ4EsEwUcXDK3EKVuBD3ENbK06BLheLeuS7A8bpamQAiEAxQTCqn81qmINz9FTVO3tqFCfPA_opSwNg8AMNzP-WME"}}