{"@context":["https://www.w3.org/ns/did/v1","https://w3id.org/security/suites/jws-2020/v1"],"id":"did:web:worldhealthorganization.github.io:tng-cdn-dev:v2.0.0:trustlist-ref:-:BHS:SCA","controller":"did:web:worldhealthorganization.github.io:tng-cdn-dev:v2.0.0:trustlist-ref:-:BHS:SCA","verificationMethod":["did:web:worldhealthorganization.github.io:tng-cdn-dev:v2.0.0:trustlist:-:BHS:SCA#vVLlfnR4nuM%3D","did:web:tng-cdn-dev.who.int:trustlist"],"proof":{"type":"JsonWebSignature2020","created":"2024-06-04T15:50:09Z","nonce":"vCBNRNC8E4Qg1mYbBSY00Log4UoY7zpX","proofPurpose":"assertionMethod","verificationMethod":"did:web:raw:githubusercontent:com:WorldHealthOrganization:tng-participants-dev:main:WHO:signing:DID","jws":"eyJiNjQiOmZhbHNlLCJjcml0IjpbImI2NCJdLCJhbGciOiJFQyJ9..MEYCIQDAlww5nakXlaK2W3c1kVIeQU1-VGPQEIUmGj1ixmeJUwIhAMQi7HThTph533HjVN96Wm0-yISCali-_HLKUDLT5g6U"}}