{"@context":["https://www.w3.org/ns/did/v1","https://w3id.org/security/suites/jws-2020/v1"],"id":"did:web:worldhealthorganization.github.io:tng-cdn-dev:v2.0.0:trustlist-ref:DCC:CHL:DSC","controller":"did:web:worldhealthorganization.github.io:tng-cdn-dev:v2.0.0:trustlist-ref:DCC:CHL:DSC","verificationMethod":["did:web:worldhealthorganization.github.io:tng-cdn-dev:v2.0.0:trustlist:DCC:CHL:DSC#aQ7BMJAhsho%3D","did:web:tng-cdn-dev.who.int:trustlist"],"proof":{"type":"JsonWebSignature2020","created":"2024-06-09T07:35:08Z","nonce":"UyTxBFAP9Y1I985Q0OEIO45D2vSAOrXX","proofPurpose":"assertionMethod","verificationMethod":"did:web:raw:githubusercontent:com:WorldHealthOrganization:tng-participants-dev:main:WHO:signing:DID","jws":"eyJiNjQiOmZhbHNlLCJjcml0IjpbImI2NCJdLCJhbGciOiJFQyJ9..MEQCIDa8A7qsReX75gxbatZyG7ksfiw9Ym2djGZCijSrGa00AiAVhNc7_SkNBfu3nA8_OBUiXIVUjiF7MoNXt1M7uk87Qw"}}